clause_segmenter/.DS_Store
clause_segmenter/ClauseSegmenter.py
clause_segmenter/__init__.py
clause_segmenter-0.1.1.dist-info/LICENSE
clause_segmenter-0.1.1.dist-info/METADATA
clause_segmenter-0.1.1.dist-info/WHEEL
clause_segmenter-0.1.1.dist-info/RECORD
