Metadata-Version: 2.1
Name: clause-segmenter
Version: 0.1.1
Summary: A clause segmenting tool utilising Python's spacy
Home-page: https://github.com/Sydney-Informatics-Hub/clause-segmenter
License: MIT
Keywords: python,spacy,nlp,clause
Author: Hamish Croser
Author-email: h.croser1@gmail.com
Requires-Python: >=3.10,<=3.13
Classifier: Intended Audience :: Developers
Classifier: Intended Audience :: Science/Research
Classifier: License :: OSI Approved :: MIT License
Classifier: Programming Language :: Python :: 3
Classifier: Programming Language :: Python :: 3.10
Classifier: Programming Language :: Python :: 3.11
Classifier: Programming Language :: Python :: 3.12
Classifier: Programming Language :: Python :: 3.13
Classifier: Topic :: Text Processing :: Linguistic
Classifier: Typing :: Typed
Requires-Dist: numpy (<2.0)
Requires-Dist: spacy (>=3.7.0,<4.0.0)
Project-URL: Documentation, https://Sydney-Informatics-Hub.github.io/clause-segmenter/DOCS.html
Project-URL: Repository, https://github.com/Sydney-Informatics-Hub/clause-segmenter
